bind_sdk/__init__.py
bind_sdk/sdk.py
bind_sdk/settings.py
bind_sdk/helpers/__init__.py
bind_sdk/helpers/is_alias.py
bind_sdk/options/__init__.py
bind_sdk/options/concept.py
bind_sdk/options/currency.py
bind_sdk/options/status.py
bind_sdk/querys/__init__.py
bind_sdk/querys/account_movements_query.py
bind_sdk/requests_payload/__init__.py
bind_sdk/requests_payload/base_payload.py
bind_sdk/requests_payload/debin_payload.py
bind_sdk/requests_payload/transfer_payload.py
bind_sdk/services/__init__.py
bind_sdk/services/bind_service.py
bind_sdk/services/cache_service.py
tests/__init__.py
tests/test_account_movements_query.py
tests/test_bind_service.py
tests/test_cache_service.py
tests/test_helpers.py
tests/test_integration.py
tests/test_options.py
tests/test_requests_payload.py
bind_sdk-1.1.0.dist-info/METADATA
bind_sdk-1.1.0.dist-info/WHEEL
bind_sdk-1.1.0.dist-info/top_level.txt
bind_sdk-1.1.0.dist-info/RECORD
