Metadata-Version: 2.1
Name: bind-sdk
Version: 1.1.0
Summary: Easy integration with BIND Argentina
Home-page: https://github.com/gustavoghioldi/bind-sdk-python
Author: Gustavo Ghioldi
Author-email: gustavoghioldi@gmail.com
Classifier: Programming Language :: Python :: 3
Classifier: License :: OSI Approved :: MIT License
Classifier: Operating System :: OS Independent
Requires-Python: >=3
